gabes/__init__.py
gabes/__main__.py
gabes/circuit.py
gabes/crypto.py
gabes/evaluator.py
gabes/garbler.py
gabes/gate.py
gabes/label.py
gabes/network.py
gabes/ot.py
gabes/settings.py
gabes/utils.py
gabes/wire.py
gabes-0.1.5.dist-info/METADATA
gabes-0.1.5.dist-info/RECORD
gabes-0.1.5.dist-info/WHEEL
gabes-0.1.5.dist-info/entry_points.txt
gabes-0.1.5.dist-info/top_level.txt
