Metadata-Version: 2.1
Name: gabes
Version: 0.1.5
Summary: A pythonic library to use Garbled Circuits
Home-page: https://github.com/nachonavarro/gabes
Author: Ignacio Navarro
Author-email: nachonavarroasv@gmail.com
License: MIT
Keywords: gabes
Platform: UNKNOWN
Classifier: Development Status :: 2 - Pre-Alpha
Classifier: Intended Audience :: Developers
Classifier: License :: OSI Approved :: MIT License
Classifier: Natural Language :: English
Classifier: Programming Language :: Python :: 3.6
Requires-Dist: wheel (>=0.22)
Requires-Dist: anytree (==2.4.3)
Requires-Dist: asn1crypto (==0.24.0)
Requires-Dist: cffi (==1.11.5)
Requires-Dist: cryptography (==2.2.2)
Requires-Dist: idna (==2.6)
Requires-Dist: mpmath (==1.0.0)
Requires-Dist: pycparser (==2.18)
Requires-Dist: pycrypto (==2.6.1)
